<?xml version="1.0" encoding="utf-8" ?>
<dwsync>
<file name="index.php" server="V:/IngeniumAcad/" local="130515030125036472" remote="130515030120000000" Dst="-1" />
<file name="index_view.php" server="V:/IngeniumAcad/" local="130515029591320760" remote="130515029590000000" Dst="-1" />
<file name="agenda.php" server="V:/IngeniumAcad/" local="130516468769032538" remote="130516468760000000" Dst="-1" />
<file name="agenda_view.php" server="V:/IngeniumAcad/" local="130516800375018659" remote="130516800370000000" Dst="-1" />
<file name="agenda_main.php" server="V:/IngeniumAcad/" local="130516769841720575" remote="130516769840000000" Dst="-1" />
<file name="agenda_main_view.php" server="V:/IngeniumAcad/" local="130516782141082633" remote="130516782140000000" Dst="-1" />
<file name="agenda_main_view_lista.php" server="V:/IngeniumAcad/" local="130516803646188405" remote="130516803640000000" Dst="-1" />
<file name="mensajes.php" server="V:/IngeniumAcad/" local="130516509390147256" remote="130516509390000000" Dst="-1" />
<file name="cursos.php" server="V:/IngeniumAcad/" local="130516440823638179" remote="130516440820000000" Dst="-1" />
<file name="notas.php" server="V:/IngeniumAcad/" local="130560866003736551" remote="130560866000000000" Dst="-1" />
<file name="faltas.php" server="V:/IngeniumAcad/" local="130516437558550003" remote="130516437550000000" Dst="-1" />
<file name="citas.php" server="V:/IngeniumAcad/" local="130516437957975753" remote="130516437950000000" Dst="-1" />
<file name="cursos_view.php" server="V:/IngeniumAcad/" local="130516822476201478" remote="130516822470000000" Dst="-1" />
<file name="mensajes_view.php" server="V:/IngeniumAcad/" local="130516605035813018" remote="130516605030000000" Dst="-1" />
<file name="mensajes_view_lista.php" server="V:/IngeniumAcad/" local="130516656385689497" remote="130516656380000000" Dst="-1" />
<file name="cursos_view_alum.php" server="V:/IngeniumAcad/" local="130516822957462323" remote="130516822950000000" Dst="-1" />
<file name="script_mens_view.php" server="V:/IngeniumAcad/" local="130542704331429531" remote="130542704330000000" Dst="0" />
<file name="notas_deta_main.php" server="V:/IngeniumAcad/" local="130564283444874639" remote="130564283440000000" Dst="0" />
<file name="notas_deta_view.php" server="V:/IngeniumAcad/" local="130606341669452613" remote="130606341660000000" Dst="0" />
<file name="notas_view.php" server="V:/IngeniumAcad/" local="130565613385194859" remote="130565613380000000" Dst="0" />
<file name="notas_view_inaccord.php" server="V:/IngeniumAcad/" local="130564273830421752" remote="130564273830000000" Dst="0" />
<file name="notas_deta_view_script.php" server="V:/IngeniumAcad/" local="130565216808880111" remote="130565216800000000" Dst="0" />
<file name="notas_deta_view_print.php" server="V:/IngeniumAcad/" local="130606359263787516" remote="130606359260000000" Dst="0" />
</dwsync>