<?xml version="1.0" encoding="utf-8" ?>
<dwsync>
<file name="robotocondensed-bold-webfont.eot" server="V:/IngeniumWebApp/" local="130505529076094495" remote="130505529070000000" Dst="0" />
<file name="robotocondensed-bold-webfont.woff" server="V:/IngeniumWebApp/" local="130505529078434499" remote="130505529070000000" Dst="0" />
<file name="robotocondensed-bold-webfont.ttf" server="V:/IngeniumWebApp/" local="130505529077810498" remote="130505529070000000" Dst="0" />
<file name="roboto-light-webfont.eot" server="V:/IngeniumWebApp/" local="130505529068450482" remote="130505529060000000" Dst="0" />
<file name="roboto-light-webfont.woff" server="V:/IngeniumWebApp/" local="130505529072662489" remote="130505529070000000" Dst="0" />
<file name="roboto-light-webfont.ttf" server="V:/IngeniumWebApp/" local="130505529071726487" remote="130505529070000000" Dst="0" />
<file name="roboto-regular-webfont.eot" server="V:/IngeniumWebApp/" local="130505529073286490" remote="130505529070000000" Dst="0" />
<file name="roboto-regular-webfont.woff" server="V:/IngeniumWebApp/" local="130505529075626494" remote="130505529070000000" Dst="0" />
<file name="roboto-regular-webfont.ttf" server="V:/IngeniumWebApp/" local="130505529074846493" remote="130505529070000000" Dst="0" />
<file name="robotocondensed-bold-webfont.eot" server="V:/IngeniumAcad/" local="130505529076094495" remote="130505529070000000" Dst="0" />
<file name="robotocondensed-bold-webfont.woff" server="V:/IngeniumAcad/" local="130505529078434499" remote="130505529070000000" Dst="0" />
<file name="robotocondensed-bold-webfont.ttf" server="V:/IngeniumAcad/" local="130505529077810498" remote="130505529070000000" Dst="0" />
<file name="roboto-light-webfont.eot" server="V:/IngeniumAcad/" local="130505529068450482" remote="130505529060000000" Dst="0" />
<file name="roboto-light-webfont.woff" server="V:/IngeniumAcad/" local="130505529072662489" remote="130505529070000000" Dst="0" />
<file name="roboto-light-webfont.ttf" server="V:/IngeniumAcad/" local="130505529071726487" remote="130505529070000000" Dst="0" />
<file name="roboto-regular-webfont.eot" server="V:/IngeniumAcad/" local="130505529073286490" remote="130505529070000000" Dst="0" />
<file name="roboto-regular-webfont.woff" server="V:/IngeniumAcad/" local="130505529075626494" remote="130505529070000000" Dst="0" />
<file name="roboto-regular-webfont.ttf" server="V:/IngeniumAcad/" local="130505529074846493" remote="130505529070000000" Dst="0" />
<file name="icomoon.eot" server="V:/IngeniumAcad/" local="130533140200000000" remote="130533140200000000" Dst="0" />
<file name="icomoon.svg" server="V:/IngeniumAcad/" local="130505529064862475" remote="130505529060000000" Dst="0" />
<file name="icomoon.ttf" server="V:/IngeniumAcad/" local="130505529065486476" remote="130505529060000000" Dst="0" />
<file name="icomoon.woff" server="V:/IngeniumAcad/" local="130505529066578478" remote="130505529060000000" Dst="0" />
<file name="roboto-light-webfont.svg" server="V:/IngeniumAcad/" local="130505529070478485" remote="130505529070000000" Dst="0" />
<file name="roboto-regular-webfont.svg" server="V:/IngeniumAcad/" local="130505529074222492" remote="130505529070000000" Dst="0" />
<file name="robotocondensed-bold-webfont.svg" server="V:/IngeniumAcad/" local="130505529077030497" remote="130505529070000000" Dst="0" />
<file name="robotocondensed-bold-webfont.eot" server="Z:/educalinks/" local="130505529076094495" remote="130505529070000000" Dst="0" />
<file name="robotocondensed-bold-webfont.woff" server="Z:/educalinks/" local="130505529078434499" remote="130505529070000000" Dst="0" />
<file name="robotocondensed-bold-webfont.ttf" server="Z:/educalinks/" local="130505529077810498" remote="130505529070000000" Dst="0" />
<file name="roboto-light-webfont.eot" server="Z:/educalinks/" local="130505529068450482" remote="130505529060000000" Dst="0" />
<file name="roboto-light-webfont.woff" server="Z:/educalinks/" local="130505529072662489" remote="130505529070000000" Dst="0" />
<file name="roboto-light-webfont.ttf" server="Z:/educalinks/" local="130505529071726487" remote="130505529070000000" Dst="0" />
<file name="roboto-regular-webfont.eot" server="Z:/educalinks/" local="130505529073286490" remote="130505529070000000" Dst="0" />
<file name="roboto-regular-webfont.woff" server="Z:/educalinks/" local="130505529075626494" remote="130505529070000000" Dst="0" />
<file name="roboto-regular-webfont.ttf" server="Z:/educalinks/" local="130505529074846493" remote="130505529070000000" Dst="0" />
<file name="icomoon.eot" server="Z:/educalinks/" local="130533140200000000" remote="130533140200000000" Dst="0" />
</dwsync>